{
    "initial": {
        "inputs": {
            "0": {
                "location": "v0",
                "size": "0x4",
                "value": "0x0"
            },
            "1": {
                "location": "v1",
                "size": "0x4",
                "value": "0x0"
            },
            "2": {
                "location": "v2",
                "size": "0x4",
                "value": "0x0"
            }
        },
        "outputs": {
            "0": {
                "location": "EAX",
                "size": "0x4",
                "value": "0xffffffff"
            }
        }
    },
    "sampling": {
        "0": {
            "inputs": {
                "0": {
                    "location": "v0",
                    "size": "0x4",
                    "value": "0x0"
                },
                "1": {
                    "location": "v1",
                    "size": "0x4",
                    "value": "0x0"
                },
                "2": {
                    "location": "v2",
                    "size": "0x4",
                    "value": "0x0"
                }
            },
            "outputs": {
                "0": {
                    "location": "EAX",
                    "size": "0x4",
                    "value": "0xffffffff"
                }
            }
        },
        "1": {
            "inputs": {
                "0": {
                    "location": "v0",
                    "size": "0x4",
                    "value": "0x1"
                },
                "1": {
                    "location": "v1",
                    "size": "0x4",
                    "value": "0x1"
                },
                "2": {
                    "location": "v2",
                    "size": "0x4",
                    "value": "0x1"
                }
            },
            "outputs": {
                "0": {
                    "location": "EAX",
                    "size": "0x4",
                    "value": "0x1"
                }
            }
        },
        "10": {
            "inputs": {
                "0": {
                    "location": "v0",
                    "size": "0x4",
                    "value": "0x2e"
                },
                "1": {
                    "location": "v1",
                    "size": "0x4",
                    "value": "0x22"
                },
                "2": {
                    "location": "v2",
                    "size": "0x4",
                    "value": "0xffffffcf"
                }
            },
            "outputs": {
                "0": {
                    "location": "EAX",
                    "size": "0x4",
                    "value": "0x8de"
                }
            }
        },
        "11": {
            "inputs": {
                "0": {
                    "location": "v0",
                    "size": "0x4",
                    "value": "0xffffffd6"
                },
                "1": {
                    "location": "v1",
                    "size": "0x4",
                    "value": "0x7"
                },
                "2": {
                    "location": "v2",
                    "size": "0x4",
                    "value": "0x14"
                }
            },
            "outputs": {
                "0": {
                    "location": "EAX",
                    "size": "0x4",
                    "value": "0xfffffca0"
                }
            }
        },
        "12": {
            "inputs": {
                "0": {
                    "location": "v0",
                    "size": "0x4",
                    "value": "0x1f"
                },
                "1": {
                    "location": "v1",
                    "size": "0x4",
                    "value": "0x1a"
                },
                "2": {
                    "location": "v2",
                    "size": "0x4",
                    "value": "0xfffffff9"
                }
            },
            "outputs": {
                "0": {
                    "location": "EAX",
                    "size": "0x4",
                    "value": "0xdd"
                }
            }
        },
        "13": {
            "inputs": {
                "0": {
                    "location": "v0",
                    "size": "0x4",
                    "value": "0x18"
                },
                "1": {
                    "location": "v1",
                    "size": "0x4",
                    "value": "0x21"
                },
                "2": {
                    "location": "v2",
                    "size": "0x4",
                    "value": "0x13"
                }
            },
            "outputs": {
                "0": {
                    "location": "EAX",
                    "size": "0x4",
                    "value": "0x1f4"
                }
            }
        },
        "14": {
            "inputs": {
                "0": {
                    "location": "v0",
                    "size": "0x4",
                    "value": "0x20"
                },
                "1": {
                    "location": "v1",
                    "size": "0x4",
                    "value": "0x1e"
                },
                "2": {
                    "location": "v2",
                    "size": "0x4",
                    "value": "0xffffffec"
                }
            },
            "outputs": {
                "0": {
                    "location": "EAX",
                    "size": "0x4",
                    "value": "0x281"
                }
            }
        },
        "15": {
            "inputs": {
                "0": {
                    "location": "v0",
                    "size": "0x4",
                    "value": "0xffffffe4"
                },
                "1": {
                    "location": "v1",
                    "size": "0x4",
                    "value": "0xffffffd4"
                },
                "2": {
                    "location": "v2",
                    "size": "0x4",
                    "value": "0xffffffd0"
                }
            },
            "outputs": {
                "0": {
                    "location": "EAX",
                    "size": "0x4",
                    "value": "0xfffffaeb"
                }
            }
        },
        "16": {
            "inputs": {
                "0": {
                    "location": "v0",
                    "size": "0x4",
                    "value": "0xffffffe3"
                },
                "1": {
                    "location": "v1",
                    "size": "0x4",
                    "value": "0x18"
                },
                "2": {
                    "location": "v2",
                    "size": "0x4",
                    "value": "0x10"
                }
            },
            "outputs": {
                "0": {
                    "location": "EAX",
                    "size": "0x4",
                    "value": "0xfffffe37"
                }
            }
        },
        "17": {
            "inputs": {
                "0": {
                    "location": "v0",
                    "size": "0x4",
                    "value": "0x11"
                },
                "1": {
                    "location": "v1",
                    "size": "0x4",
                    "value": "0xc"
                },
                "2": {
                    "location": "v2",
                    "size": "0x4",
                    "value": "0x7"
                }
            },
            "outputs": {
                "0": {
                    "location": "EAX",
                    "size": "0x4",
                    "value": "0x79"
                }
            }
        },
        "18": {
            "inputs": {
                "0": {
                    "location": "v0",
                    "size": "0x4",
                    "value": "0x24"
                },
                "1": {
                    "location": "v1",
                    "size": "0x4",
                    "value": "0xb"
                },
                "2": {
                    "location": "v2",
                    "size": "0x4",
                    "value": "0xffffffe5"
                }
            },
            "outputs": {
                "0": {
                    "location": "EAX",
                    "size": "0x4",
                    "value": "0x3dc"
                }
            }
        },
        "19": {
            "inputs": {
                "0": {
                    "location": "v0",
                    "size": "0x4",
                    "value": "0xfffffff4"
                },
                "1": {
                    "location": "v1",
                    "size": "0x4",
                    "value": "0x22"
                },
                "2": {
                    "location": "v2",
                    "size": "0x4",
                    "value": "0x2e"
                }
            },
            "outputs": {
                "0": {
                    "location": "EAX",
                    "size": "0x4",
                    "value": "0xfffffdf9"
                }
            }
        },
        "2": {
            "inputs": {
                "0": {
                    "location": "v0",
                    "size": "0x4",
                    "value": "0xffffffff"
                },
                "1": {
                    "location": "v1",
                    "size": "0x4",
                    "value": "0xffffffff"
                },
                "2": {
                    "location": "v2",
                    "size": "0x4",
                    "value": "0xffffffff"
                }
            },
            "outputs": {
                "0": {
                    "location": "EAX",
                    "size": "0x4",
                    "value": "0xffffffff"
                }
            }
        },
        "20": {
            "inputs": {
                "0": {
                    "location": "v0",
                    "size": "0x4",
                    "value": "0x27"
                },
                "1": {
                    "location": "v1",
                    "size": "0x4",
                    "value": "0xffffffdc"
                },
                "2": {
                    "location": "v2",
                    "size": "0x4",
                    "value": "0xfffffffe"
                }
            },
            "outputs": {
                "0": {
                    "location": "EAX",
                    "size": "0x4",
                    "value": "0x4f"
                }
            }
        },
        "21": {
            "inputs": {
                "0": {
                    "location": "v0",
                    "size": "0x4",
                    "value": "0x18"
                },
                "1": {
                    "location": "v1",
                    "size": "0x4",
                    "value": "0x2"
                },
                "2": {
                    "location": "v2",
                    "size": "0x4",
                    "value": "0xd"
                }
            },
            "outputs": {
                "0": {
                    "location": "EAX",
                    "size": "0x4",
                    "value": "0x138"
                }
            }
        },
        "22": {
            "inputs": {
                "0": {
                    "location": "v0",
                    "size": "0x4",
                    "value": "0x2a"
                },
                "1": {
                    "location": "v1",
                    "size": "0x4",
                    "value": "0xffffffd3"
                },
                "2": {
                    "location": "v2",
                    "size": "0x4",
                    "value": "0x2"
                }
            },
            "outputs": {
                "0": {
                    "location": "EAX",
                    "size": "0x4",
                    "value": "0xffffff80"
                }
            }
        },
        "23": {
            "inputs": {
                "0": {
                    "location": "v0",
                    "size": "0x4",
                    "value": "0xfffffffd"
                },
                "1": {
                    "location": "v1",
                    "size": "0x4",
                    "value": "0xffffffe8"
                },
                "2": {
                    "location": "v2",
                    "size": "0x4",
                    "value": "0xb"
                }
            },
            "outputs": {
                "0": {
                    "location": "EAX",
                    "size": "0x4",
                    "value": "0x35"
                }
            }
        },
        "24": {
            "inputs": {
                "0": {
                    "location": "v0",
                    "size": "0x4",
                    "value": "0x7"
                },
                "1": {
                    "location": "v1",
                    "size": "0x4",
                    "value": "0xffffffe8"
                },
                "2": {
                    "location": "v2",
                    "size": "0x4",
                    "value": "0xffffffed"
                }
            },
            "outputs": {
                "0": {
                    "location": "EAX",
                    "size": "0x4",
                    "value": "0x97"
                }
            }
        },
        "25": {
            "inputs": {
                "0": {
                    "location": "v0",
                    "size": "0x4",
                    "value": "0xd"
                },
                "1": {
                    "location": "v1",
                    "size": "0x4",
                    "value": "0x23"
                },
                "2": {
                    "location": "v2",
                    "size": "0x4",
                    "value": "0x2a"
                }
            },
            "outputs": {
                "0": {
                    "location": "EAX",
                    "size": "0x4",
                    "value": "0x20a"
                }
            }
        },
        "26": {
            "inputs": {
                "0": {
                    "location": "v0",
                    "size": "0x4",
                    "value": "0x30"
                },
                "1": {
                    "location": "v1",
                    "size": "0x4",
                    "value": "0xffffffe9"
                },
                "2": {
                    "location": "v2",
                    "size": "0x4",
                    "value": "0x1b"
                }
            },
            "outputs": {
                "0": {
                    "location": "EAX",
                    "size": "0x4",
                    "value": "0xfffffaf4"
                }
            }
        },
        "27": {
            "inputs": {
                "0": {
                    "location": "v0",
                    "size": "0x4",
                    "value": "0xffffffe7"
                },
                "1": {
                    "location": "v1",
                    "size": "0x4",
                    "value": "0x15"
                },
                "2": {
                    "location": "v2",
                    "size": "0x4",
                    "value": "0x3"
                }
            },
            "outputs": {
                "0": {
                    "location": "EAX",
                    "size": "0x4",
                    "value": "0xffffffa3"
                }
            }
        },
        "28": {
            "inputs": {
                "0": {
                    "location": "v0",
                    "size": "0x4",
                    "value": "0x0"
                },
                "1": {
                    "location": "v1",
                    "size": "0x4",
                    "value": "0xffffffd6"
                },
                "2": {
                    "location": "v2",
                    "size": "0x4",
                    "value": "0xe"
                }
            },
            "outputs": {
                "0": {
                    "location": "EAX",
                    "size": "0x4",
                    "value": "0x21"
                }
            }
        },
        "29": {
            "inputs": {
                "0": {
                    "location": "v0",
                    "size": "0x4",
                    "value": "0x5"
                },
                "1": {
                    "location": "v1",
                    "size": "0x4",
                    "value": "0xffffffd0"
                },
                "2": {
                    "location": "v2",
                    "size": "0x4",
                    "value": "0x12"
                }
            },
            "outputs": {
                "0": {
                    "location": "EAX",
                    "size": "0x4",
                    "value": "0xffffff8b"
                }
            }
        },
        "3": {
            "inputs": {
                "0": {
                    "location": "v0",
                    "size": "0x4",
                    "value": "0x7fffffff"
                },
                "1": {
                    "location": "v1",
                    "size": "0x4",
                    "value": "0x7fffffff"
                },
                "2": {
                    "location": "v2",
                    "size": "0x4",
                    "value": "0x7fffffff"
                }
            },
            "outputs": {
                "0": {
                    "location": "EAX",
                    "size": "0x4",
                    "value": "0x7fffffff"
                }
            }
        },
        "30": {
            "inputs": {
                "0": {
                    "location": "v0",
                    "size": "0x4",
                    "value": "0xfffffffe"
                },
                "1": {
                    "location": "v1",
                    "size": "0x4",
                    "value": "0xfffffff8"
                },
                "2": {
                    "location": "v2",
                    "size": "0x4",
                    "value": "0x2c"
                }
            },
            "outputs": {
                "0": {
                    "location": "EAX",
                    "size": "0x4",
                    "value": "0x5b"
                }
            }
        },
        "31": {
            "inputs": {
                "0": {
                    "location": "v0",
                    "size": "0x4",
                    "value": "0x1a"
                },
                "1": {
                    "location": "v1",
                    "size": "0x4",
                    "value": "0xffffffe2"
                },
                "2": {
                    "location": "v2",
                    "size": "0x4",
                    "value": "0xffffffda"
                }
            },
            "outputs": {
                "0": {
                    "location": "EAX",
                    "size": "0x4",
                    "value": "0x3d9"
                }
            }
        },
        "32": {
            "inputs": {
                "0": {
                    "location": "v0",
                    "size": "0x4",
                    "value": "0xfffffff2"
                },
                "1": {
                    "location": "v1",
                    "size": "0x4",
                    "value": "0x2e"
                },
                "2": {
                    "location": "v2",
                    "size": "0x4",
                    "value": "0x2c"
                }
            },
            "outputs": {
                "0": {
                    "location": "EAX",
                    "size": "0x4",
                    "value": "0xfffffdb9"
                }
            }
        },
        "33": {
            "inputs": {
                "0": {
                    "location": "v0",
                    "size": "0x4",
                    "value": "0xffffffe6"
                },
                "1": {
                    "location": "v1",
                    "size": "0x4",
                    "value": "0xffffffe9"
                },
                "2": {
                    "location": "v2",
                    "size": "0x4",
                    "value": "0xffffffdd"
                }
            },
            "outputs": {
                "0": {
                    "location": "EAX",
                    "size": "0x4",
                    "value": "0xfffffc70"
                }
            }
        },
        "34": {
            "inputs": {
                "0": {
                    "location": "v0",
                    "size": "0x4",
                    "value": "0x8"
                },
                "1": {
                    "location": "v1",
                    "size": "0x4",
                    "value": "0xffffffce"
                },
                "2": {
                    "location": "v2",
                    "size": "0x4",
                    "value": "0xfffffffc"
                }
            },
            "outputs": {
                "0": {
                    "location": "EAX",
                    "size": "0x4",
                    "value": "0x21"
                }
            }
        },
        "35": {
            "inputs": {
                "0": {
                    "location": "v0",
                    "size": "0x4",
                    "value": "0x30"
                },
                "1": {
                    "location": "v1",
                    "size": "0x4",
                    "value": "0x1c"
                },
                "2": {
                    "location": "v2",
                    "size": "0x4",
                    "value": "0x1e"
                }
            },
            "outputs": {
                "0": {
                    "location": "EAX",
                    "size": "0x4",
                    "value": "0x581"
                }
            }
        },
        "36": {
            "inputs": {
                "0": {
                    "location": "v0",
                    "size": "0x4",
                    "value": "0x1b"
                },
                "1": {
                    "location": "v1",
                    "size": "0x4",
                    "value": "0xd"
                },
                "2": {
                    "location": "v2",
                    "size": "0x4",
                    "value": "0x18"
                }
            },
            "outputs": {
                "0": {
                    "location": "EAX",
                    "size": "0x4",
                    "value": "0x29a"
                }
            }
        },
        "37": {
            "inputs": {
                "0": {
                    "location": "v0",
                    "size": "0x4",
                    "value": "0xffffffee"
                },
                "1": {
                    "location": "v1",
                    "size": "0x4",
                    "value": "0x23"
                },
                "2": {
                    "location": "v2",
                    "size": "0x4",
                    "value": "0xffffffdd"
                }
            },
            "outputs": {
                "0": {
                    "location": "EAX",
                    "size": "0x4",
                    "value": "0xfffffd8a"
                }
            }
        },
        "38": {
            "inputs": {
                "0": {
                    "location": "v0",
                    "size": "0x4",
                    "value": "0xffffffed"
                },
                "1": {
                    "location": "v1",
                    "size": "0x4",
                    "value": "0x4"
                },
                "2": {
                    "location": "v2",
                    "size": "0x4",
                    "value": "0x14"
                }
            },
            "outputs": {
                "0": {
                    "location": "EAX",
                    "size": "0x4",
                    "value": "0xfffffe97"
                }
            }
        },
        "39": {
            "inputs": {
                "0": {
                    "location": "v0",
                    "size": "0x4",
                    "value": "0xffffffe1"
                },
                "1": {
                    "location": "v1",
                    "size": "0x4",
                    "value": "0xffffffe9"
                },
                "2": {
                    "location": "v2",
                    "size": "0x4",
                    "value": "0xffffffe9"
                }
            },
            "outputs": {
                "0": {
                    "location": "EAX",
                    "size": "0x4",
                    "value": "0xfffffd21"
                }
            }
        },
        "4": {
            "inputs": {
                "0": {
                    "location": "v0",
                    "size": "0x4",
                    "value": "0x80000000"
                },
                "1": {
                    "location": "v1",
                    "size": "0x4",
                    "value": "0x80000000"
                },
                "2": {
                    "location": "v2",
                    "size": "0x4",
                    "value": "0x80000000"
                }
            },
            "outputs": {
                "0": {
                    "location": "EAX",
                    "size": "0x4",
                    "value": "0x7fffffff"
                }
            }
        },
        "40": {
            "inputs": {
                "0": {
                    "location": "v0",
                    "size": "0x4",
                    "value": "0x30"
                },
                "1": {
                    "location": "v1",
                    "size": "0x4",
                    "value": "0xfffffff3"
                },
                "2": {
                    "location": "v2",
                    "size": "0x4",
                    "value": "0x30"
                }
            },
            "outputs": {
                "0": {
                    "location": "EAX",
                    "size": "0x4",
                    "value": "0xfffff70c"
                }
            }
        },
        "41": {
            "inputs": {
                "0": {
                    "location": "v0",
                    "size": "0x4",
                    "value": "0xffffffd9"
                },
                "1": {
                    "location": "v1",
                    "size": "0x4",
                    "value": "0xffffffe2"
                },
                "2": {
                    "location": "v2",
                    "size": "0x4",
                    "value": "0xffffffda"
                }
            },
            "outputs": {
                "0": {
                    "location": "EAX",
                    "size": "0x4",
                    "value": "0xfffffa33"
                }
            }
        },
        "42": {
            "inputs": {
                "0": {
                    "location": "v0",
                    "size": "0x4",
                    "value": "0x10"
                },
                "1": {
                    "location": "v1",
                    "size": "0x4",
                    "value": "0x9"
                },
                "2": {
                    "location": "v2",
                    "size": "0x4",
                    "value": "0xfffffff9"
                }
            },
            "outputs": {
                "0": {
                    "location": "EAX",
                    "size": "0x4",
                    "value": "0x76"
                }
            }
        },
        "43": {
            "inputs": {
                "0": {
                    "location": "v0",
                    "size": "0x4",
                    "value": "0xd"
                },
                "1": {
                    "location": "v1",
                    "size": "0x4",
                    "value": "0xffffffe4"
                },
                "2": {
                    "location": "v2",
                    "size": "0x4",
                    "value": "0x15"
                }
            },
            "outputs": {
                "0": {
                    "location": "EAX",
                    "size": "0x4",
                    "value": "0xfffffee5"
                }
            }
        },
        "44": {
            "inputs": {
                "0": {
                    "location": "v0",
                    "size": "0x4",
                    "value": "0x27"
                },
                "1": {
                    "location": "v1",
                    "size": "0x4",
                    "value": "0xfffffff5"
                },
                "2": {
                    "location": "v2",
                    "size": "0x4",
                    "value": "0xffffffee"
                }
            },
            "outputs": {
                "0": {
                    "location": "EAX",
                    "size": "0x4",
                    "value": "0x2be"
                }
            }
        },
        "45": {
            "inputs": {
                "0": {
                    "location": "v0",
                    "size": "0x4",
                    "value": "0xfffffff4"
                },
                "1": {
                    "location": "v1",
                    "size": "0x4",
                    "value": "0xffffffea"
                },
                "2": {
                    "location": "v2",
                    "size": "0x4",
                    "value": "0xffffffef"
                }
            },
            "outputs": {
                "0": {
                    "location": "EAX",
                    "size": "0x4",
                    "value": "0xffffff24"
                }
            }
        },
        "46": {
            "inputs": {
                "0": {
                    "location": "v0",
                    "size": "0x4",
                    "value": "0xfffffff8"
                },
                "1": {
                    "location": "v1",
                    "size": "0x4",
                    "value": "0xffffffd0"
                },
                "2": {
                    "location": "v2",
                    "size": "0x4",
                    "value": "0xffffffee"
                }
            },
            "outputs": {
                "0": {
                    "location": "EAX",
                    "size": "0x4",
                    "value": "0xffffff71"
                }
            }
        },
        "47": {
            "inputs": {
                "0": {
                    "location": "v0",
                    "size": "0x4",
                    "value": "0x23"
                },
                "1": {
                    "location": "v1",
                    "size": "0x4",
                    "value": "0xa"
                },
                "2": {
                    "location": "v2",
                    "size": "0x4",
                    "value": "0xfffffffd"
                }
            },
            "outputs": {
                "0": {
                    "location": "EAX",
                    "size": "0x4",
                    "value": "0x69"
                }
            }
        },
        "48": {
            "inputs": {
                "0": {
                    "location": "v0",
                    "size": "0x4",
                    "value": "0xfffffff2"
                },
                "1": {
                    "location": "v1",
                    "size": "0x4",
                    "value": "0x4"
                },
                "2": {
                    "location": "v2",
                    "size": "0x4",
                    "value": "0x11"
                }
            },
            "outputs": {
                "0": {
                    "location": "EAX",
                    "size": "0x4",
                    "value": "0xffffff04"
                }
            }
        },
        "49": {
            "inputs": {
                "0": {
                    "location": "v0",
                    "size": "0x4",
                    "value": "0x2f"
                },
                "1": {
                    "location": "v1",
                    "size": "0x4",
                    "value": "0xfffffff4"
                },
                "2": {
                    "location": "v2",
                    "size": "0x4",
                    "value": "0x19"
                }
            },
            "outputs": {
                "0": {
                    "location": "EAX",
                    "size": "0x4",
                    "value": "0xfffffb6b"
                }
            }
        },
        "5": {
            "inputs": {
                "0": {
                    "location": "v0",
                    "size": "0x4",
                    "value": "0xffffffe7"
                },
                "1": {
                    "location": "v1",
                    "size": "0x4",
                    "value": "0xb"
                },
                "2": {
                    "location": "v2",
                    "size": "0x4",
                    "value": "0x25"
                }
            },
            "outputs": {
                "0": {
                    "location": "EAX",
                    "size": "0x4",
                    "value": "0xfffffc4d"
                }
            }
        },
        "50": {
            "inputs": {
                "0": {
                    "location": "v0",
                    "size": "0x4",
                    "value": "0xffffffce"
                },
                "1": {
                    "location": "v1",
                    "size": "0x4",
                    "value": "0x29"
                },
                "2": {
                    "location": "v2",
                    "size": "0x4",
                    "value": "0x17"
                }
            },
            "outputs": {
                "0": {
                    "location": "EAX",
                    "size": "0x4",
                    "value": "0xfffffbbe"
                }
            }
        },
        "51": {
            "inputs": {
                "0": {
                    "location": "v0",
                    "size": "0x4",
                    "value": "0x1"
                },
                "1": {
                    "location": "v1",
                    "size": "0x4",
                    "value": "0x4"
                },
                "2": {
                    "location": "v2",
                    "size": "0x4",
                    "value": "0x4"
                }
            },
            "outputs": {
                "0": {
                    "location": "EAX",
                    "size": "0x4",
                    "value": "0x7"
                }
            }
        },
        "52": {
            "inputs": {
                "0": {
                    "location": "v0",
                    "size": "0x4",
                    "value": "0x2"
                },
                "1": {
                    "location": "v1",
                    "size": "0x4",
                    "value": "0x8"
                },
                "2": {
                    "location": "v2",
                    "size": "0x4",
                    "value": "0xffffffd6"
                }
            },
            "outputs": {
                "0": {
                    "location": "EAX",
                    "size": "0x4",
                    "value": "0x75"
                }
            }
        },
        "53": {
            "inputs": {
                "0": {
                    "location": "v0",
                    "size": "0x4",
                    "value": "0xffffffdb"
                },
                "1": {
                    "location": "v1",
                    "size": "0x4",
                    "value": "0x6"
                },
                "2": {
                    "location": "v2",
                    "size": "0x4",
                    "value": "0xb"
                }
            },
            "outputs": {
                "0": {
                    "location": "EAX",
                    "size": "0x4",
                    "value": "0xfffffe67"
                }
            }
        },
        "54": {
            "inputs": {
                "0": {
                    "location": "v0",
                    "size": "0x4",
                    "value": "0x24"
                },
                "1": {
                    "location": "v1",
                    "size": "0x4",
                    "value": "0x28"
                },
                "2": {
                    "location": "v2",
                    "size": "0x4",
                    "value": "0xffffffdf"
                }
            },
            "outputs": {
                "0": {
                    "location": "EAX",
                    "size": "0x4",
                    "value": "0x4a4"
                }
            }
        },
        "55": {
            "inputs": {
                "0": {
                    "location": "v0",
                    "size": "0x4",
                    "value": "0x1a"
                },
                "1": {
                    "location": "v1",
                    "size": "0x4",
                    "value": "0x2c"
                },
                "2": {
                    "location": "v2",
                    "size": "0x4",
                    "value": "0xfffffffa"
                }
            },
            "outputs": {
                "0": {
                    "location": "EAX",
                    "size": "0x4",
                    "value": "0x9d"
                }
            }
        },
        "56": {
            "inputs": {
                "0": {
                    "location": "v0",
                    "size": "0x4",
                    "value": "0x8"
                },
                "1": {
                    "location": "v1",
                    "size": "0x4",
                    "value": "0x16"
                },
                "2": {
                    "location": "v2",
                    "size": "0x4",
                    "value": "0x8"
                }
            },
            "outputs": {
                "0": {
                    "location": "EAX",
                    "size": "0x4",
                    "value": "0x21"
                }
            }
        },
        "57": {
            "inputs": {
                "0": {
                    "location": "v0",
                    "size": "0x4",
                    "value": "0xffffffff"
                },
                "1": {
                    "location": "v1",
                    "size": "0x4",
                    "value": "0x25"
                },
                "2": {
                    "location": "v2",
                    "size": "0x4",
                    "value": "0x17"
                }
            },
            "outputs": {
                "0": {
                    "location": "EAX",
                    "size": "0x4",
                    "value": "0xffffffdf"
                }
            }
        },
        "58": {
            "inputs": {
                "0": {
                    "location": "v0",
                    "size": "0x4",
                    "value": "0xfffffff4"
                },
                "1": {
                    "location": "v1",
                    "size": "0x4",
                    "value": "0xffffffe3"
                },
                "2": {
                    "location": "v2",
                    "size": "0x4",
                    "value": "0x4"
                }
            },
            "outputs": {
                "0": {
                    "location": "EAX",
                    "size": "0x4",
                    "value": "0x28"
                }
            }
        },
        "59": {
            "inputs": {
                "0": {
                    "location": "v0",
                    "size": "0x4",
                    "value": "0xffffffd8"
                },
                "1": {
                    "location": "v1",
                    "size": "0x4",
                    "value": "0xfffffffd"
                },
                "2": {
                    "location": "v2",
                    "size": "0x4",
                    "value": "0x1b"
                }
            },
            "outputs": {
                "0": {
                    "location": "EAX",
                    "size": "0x4",
                    "value": "0x438"
                }
            }
        },
        "6": {
            "inputs": {
                "0": {
                    "location": "v0",
                    "size": "0x4",
                    "value": "0xa"
                },
                "1": {
                    "location": "v1",
                    "size": "0x4",
                    "value": "0x27"
                },
                "2": {
                    "location": "v2",
                    "size": "0x4",
                    "value": "0xfffffffd"
                }
            },
            "outputs": {
                "0": {
                    "location": "EAX",
                    "size": "0x4",
                    "value": "0x1e"
                }
            }
        },
        "60": {
            "inputs": {
                "0": {
                    "location": "v0",
                    "size": "0x4",
                    "value": "0xfffffffd"
                },
                "1": {
                    "location": "v1",
                    "size": "0x4",
                    "value": "0xffffffd6"
                },
                "2": {
                    "location": "v2",
                    "size": "0x4",
                    "value": "0xffffffd0"
                }
            },
            "outputs": {
                "0": {
                    "location": "EAX",
                    "size": "0x4",
                    "value": "0xffffff59"
                }
            }
        },
        "61": {
            "inputs": {
                "0": {
                    "location": "v0",
                    "size": "0x4",
                    "value": "0x30"
                },
                "1": {
                    "location": "v1",
                    "size": "0x4",
                    "value": "0xffffffd2"
                },
                "2": {
                    "location": "v2",
                    "size": "0x4",
                    "value": "0xfffffff0"
                }
            },
            "outputs": {
                "0": {
                    "location": "EAX",
                    "size": "0x4",
                    "value": "0x30d"
                }
            }
        },
        "62": {
            "inputs": {
                "0": {
                    "location": "v0",
                    "size": "0x4",
                    "value": "0x2e"
                },
                "1": {
                    "location": "v1",
                    "size": "0x4",
                    "value": "0xffffffd9"
                },
                "2": {
                    "location": "v2",
                    "size": "0x4",
                    "value": "0x13"
                }
            },
            "outputs": {
                "0": {
                    "location": "EAX",
                    "size": "0x4",
                    "value": "0xfffffcb2"
                }
            }
        },
        "63": {
            "inputs": {
                "0": {
                    "location": "v0",
                    "size": "0x4",
                    "value": "0x1e"
                },
                "1": {
                    "location": "v1",
                    "size": "0x4",
                    "value": "0x2f"
                },
                "2": {
                    "location": "v2",
                    "size": "0x4",
                    "value": "0xffffffea"
                }
            },
            "outputs": {
                "0": {
                    "location": "EAX",
                    "size": "0x4",
                    "value": "0x284"
                }
            }
        },
        "64": {
            "inputs": {
                "0": {
                    "location": "v0",
                    "size": "0x4",
                    "value": "0x16"
                },
                "1": {
                    "location": "v1",
                    "size": "0x4",
                    "value": "0xffffffd1"
                },
                "2": {
                    "location": "v2",
                    "size": "0x4",
                    "value": "0x1b"
                }
            },
            "outputs": {
                "0": {
                    "location": "EAX",
                    "size": "0x4",
                    "value": "0xfffffd8a"
                }
            }
        },
        "65": {
            "inputs": {
                "0": {
                    "location": "v0",
                    "size": "0x4",
                    "value": "0xfffffff6"
                },
                "1": {
                    "location": "v1",
                    "size": "0x4",
                    "value": "0xfffffff6"
                },
                "2": {
                    "location": "v2",
                    "size": "0x4",
                    "value": "0xffffffcf"
                }
            },
            "outputs": {
                "0": {
                    "location": "EAX",
                    "size": "0x4",
                    "value": "0xfffffe16"
                }
            }
        },
        "66": {
            "inputs": {
                "0": {
                    "location": "v0",
                    "size": "0x4",
                    "value": "0x2"
                },
                "1": {
                    "location": "v1",
                    "size": "0x4",
                    "value": "0x1d"
                },
                "2": {
                    "location": "v2",
                    "size": "0x4",
                    "value": "0x2"
                }
            },
            "outputs": {
                "0": {
                    "location": "EAX",
                    "size": "0x4",
                    "value": "0x1c"
                }
            }
        },
        "67": {
            "inputs": {
                "0": {
                    "location": "v0",
                    "size": "0x4",
                    "value": "0xffffffd1"
                },
                "1": {
                    "location": "v1",
                    "size": "0x4",
                    "value": "0xfffffff4"
                },
                "2": {
                    "location": "v2",
                    "size": "0x4",
                    "value": "0x14"
                }
            },
            "outputs": {
                "0": {
                    "location": "EAX",
                    "size": "0x4",
                    "value": "0x3a7"
                }
            }
        },
        "68": {
            "inputs": {
                "0": {
                    "location": "v0",
                    "size": "0x4",
                    "value": "0x27"
                },
                "1": {
                    "location": "v1",
                    "size": "0x4",
                    "value": "0x0"
                },
                "2": {
                    "location": "v2",
                    "size": "0x4",
                    "value": "0xffffffe1"
                }
            },
            "outputs": {
                "0": {
                    "location": "EAX",
                    "size": "0x4",
                    "value": "0x4a7"
                }
            }
        },
        "69": {
            "inputs": {
                "0": {
                    "location": "v0",
                    "size": "0x4",
                    "value": "0xfffffff9"
                },
                "1": {
                    "location": "v1",
                    "size": "0x4",
                    "value": "0x23"
                },
                "2": {
                    "location": "v2",
                    "size": "0x4",
                    "value": "0x19"
                }
            },
            "outputs": {
                "0": {
                    "location": "EAX",
                    "size": "0x4",
                    "value": "0xffffff6b"
                }
            }
        },
        "7": {
            "inputs": {
                "0": {
                    "location": "v0",
                    "size": "0x4",
                    "value": "0x32"
                },
                "1": {
                    "location": "v1",
                    "size": "0x4",
                    "value": "0xffffffce"
                },
                "2": {
                    "location": "v2",
                    "size": "0x4",
                    "value": "0xffffffcf"
                }
            },
            "outputs": {
                "0": {
                    "location": "EAX",
                    "size": "0x4",
                    "value": "0x9a2"
                }
            }
        },
        "70": {
            "inputs": {
                "0": {
                    "location": "v0",
                    "size": "0x4",
                    "value": "0xffffffd1"
                },
                "1": {
                    "location": "v1",
                    "size": "0x4",
                    "value": "0x15"
                },
                "2": {
                    "location": "v2",
                    "size": "0x4",
                    "value": "0xfffffffd"
                }
            },
            "outputs": {
                "0": {
                    "location": "EAX",
                    "size": "0x4",
                    "value": "0xffffff71"
                }
            }
        },
        "71": {
            "inputs": {
                "0": {
                    "location": "v0",
                    "size": "0x4",
                    "value": "0xffffffce"
                },
                "1": {
                    "location": "v1",
                    "size": "0x4",
                    "value": "0x1e"
                },
                "2": {
                    "location": "v2",
                    "size": "0x4",
                    "value": "0x28"
                }
            },
            "outputs": {
                "0": {
                    "location": "EAX",
                    "size": "0x4",
                    "value": "0xfffff811"
                }
            }
        },
        "72": {
            "inputs": {
                "0": {
                    "location": "v0",
                    "size": "0x4",
                    "value": "0xfffffff2"
                },
                "1": {
                    "location": "v1",
                    "size": "0x4",
                    "value": "0x23"
                },
                "2": {
                    "location": "v2",
                    "size": "0x4",
                    "value": "0xfffffff7"
                }
            },
            "outputs": {
                "0": {
                    "location": "EAX",
                    "size": "0x4",
                    "value": "0xffffff8a"
                }
            }
        },
        "73": {
            "inputs": {
                "0": {
                    "location": "v0",
                    "size": "0x4",
                    "value": "0xffffffd6"
                },
                "1": {
                    "location": "v1",
                    "size": "0x4",
                    "value": "0x1a"
                },
                "2": {
                    "location": "v2",
                    "size": "0x4",
                    "value": "0xffffffce"
                }
            },
            "outputs": {
                "0": {
                    "location": "EAX",
                    "size": "0x4",
                    "value": "0xfffff7ed"
                }
            }
        },
        "74": {
            "inputs": {
                "0": {
                    "location": "v0",
                    "size": "0x4",
                    "value": "0xb"
                },
                "1": {
                    "location": "v1",
                    "size": "0x4",
                    "value": "0x10"
                },
                "2": {
                    "location": "v2",
                    "size": "0x4",
                    "value": "0xfffffff1"
                }
            },
            "outputs": {
                "0": {
                    "location": "EAX",
                    "size": "0x4",
                    "value": "0xab"
                }
            }
        },
        "75": {
            "inputs": {
                "0": {
                    "location": "v0",
                    "size": "0x4",
                    "value": "0x32"
                },
                "1": {
                    "location": "v1",
                    "size": "0x4",
                    "value": "0x18"
                },
                "2": {
                    "location": "v2",
                    "size": "0x4",
                    "value": "0x7"
                }
            },
            "outputs": {
                "0": {
                    "location": "EAX",
                    "size": "0x4",
                    "value": "0x142"
                }
            }
        },
        "76": {
            "inputs": {
                "0": {
                    "location": "v0",
                    "size": "0x4",
                    "value": "0xd"
                },
                "1": {
                    "location": "v1",
                    "size": "0x4",
                    "value": "0x2"
                },
                "2": {
                    "location": "v2",
                    "size": "0x4",
                    "value": "0x2c"
                }
            },
            "outputs": {
                "0": {
                    "location": "EAX",
                    "size": "0x4",
                    "value": "0x215"
                }
            }
        },
        "77": {
            "inputs": {
                "0": {
                    "location": "v0",
                    "size": "0x4",
                    "value": "0x28"
                },
                "1": {
                    "location": "v1",
                    "size": "0x4",
                    "value": "0x6"
                },
                "2": {
                    "location": "v2",
                    "size": "0x4",
                    "value": "0xffffffd0"
                }
            },
            "outputs": {
                "0": {
                    "location": "EAX",
                    "size": "0x4",
                    "value": "0x7a9"
                }
            }
        },
        "78": {
            "inputs": {
                "0": {
                    "location": "v0",
                    "size": "0x4",
                    "value": "0x2d"
                },
                "1": {
                    "location": "v1",
                    "size": "0x4",
                    "value": "0x15"
                },
                "2": {
                    "location": "v2",
                    "size": "0x4",
                    "value": "0x7"
                }
            },
            "outputs": {
                "0": {
                    "location": "EAX",
                    "size": "0x4",
                    "value": "0x12d"
                }
            }
        },
        "79": {
            "inputs": {
                "0": {
                    "location": "v0",
                    "size": "0x4",
                    "value": "0x10"
                },
                "1": {
                    "location": "v1",
                    "size": "0x4",
                    "value": "0xfffffffd"
                },
                "2": {
                    "location": "v2",
                    "size": "0x4",
                    "value": "0x22"
                }
            },
            "outputs": {
                "0": {
                    "location": "EAX",
                    "size": "0x4",
                    "value": "0xfffffde0"
                }
            }
        },
        "8": {
            "inputs": {
                "0": {
                    "location": "v0",
                    "size": "0x4",
                    "value": "0xffffffff"
                },
                "1": {
                    "location": "v1",
                    "size": "0x4",
                    "value": "0xc"
                },
                "2": {
                    "location": "v2",
                    "size": "0x4",
                    "value": "0x8"
                }
            },
            "outputs": {
                "0": {
                    "location": "EAX",
                    "size": "0x4",
                    "value": "0xfffffffb"
                }
            }
        },
        "80": {
            "inputs": {
                "0": {
                    "location": "v0",
                    "size": "0x4",
                    "value": "0xffffffdb"
                },
                "1": {
                    "location": "v1",
                    "size": "0x4",
                    "value": "0xffffffe9"
                },
                "2": {
                    "location": "v2",
                    "size": "0x4",
                    "value": "0x2c"
                }
            },
            "outputs": {
                "0": {
                    "location": "EAX",
                    "size": "0x4",
                    "value": "0x64e"
                }
            }
        },
        "81": {
            "inputs": {
                "0": {
                    "location": "v0",
                    "size": "0x4",
                    "value": "0x31"
                },
                "1": {
                    "location": "v1",
                    "size": "0x4",
                    "value": "0xffffffee"
                },
                "2": {
                    "location": "v2",
                    "size": "0x4",
                    "value": "0x29"
                }
            },
            "outputs": {
                "0": {
                    "location": "EAX",
                    "size": "0x4",
                    "value": "0xfffff837"
                }
            }
        },
        "82": {
            "inputs": {
                "0": {
                    "location": "v0",
                    "size": "0x4",
                    "value": "0x1f"
                },
                "1": {
                    "location": "v1",
                    "size": "0x4",
                    "value": "0xa"
                },
                "2": {
                    "location": "v2",
                    "size": "0x4",
                    "value": "0xfffffffc"
                }
            },
            "outputs": {
                "0": {
                    "location": "EAX",
                    "size": "0x4",
                    "value": "0x7d"
                }
            }
        },
        "83": {
            "inputs": {
                "0": {
                    "location": "v0",
                    "size": "0x4",
                    "value": "0xffffffec"
                },
                "1": {
                    "location": "v1",
                    "size": "0x4",
                    "value": "0x1d"
                },
                "2": {
                    "location": "v2",
                    "size": "0x4",
                    "value": "0xfffffff3"
                }
            },
            "outputs": {
                "0": {
                    "location": "EAX",
                    "size": "0x4",
                    "value": "0xfffffefc"
                }
            }
        },
        "84": {
            "inputs": {
                "0": {
                    "location": "v0",
                    "size": "0x4",
                    "value": "0x2"
                },
                "1": {
                    "location": "v1",
                    "size": "0x4",
                    "value": "0x16"
                },
                "2": {
                    "location": "v2",
                    "size": "0x4",
                    "value": "0xffffffda"
                }
            },
            "outputs": {
                "0": {
                    "location": "EAX",
                    "size": "0x4",
                    "value": "0x6d"
                }
            }
        },
        "85": {
            "inputs": {
                "0": {
                    "location": "v0",
                    "size": "0x4",
                    "value": "0xfffffff7"
                },
                "1": {
                    "location": "v1",
                    "size": "0x4",
                    "value": "0xa"
                },
                "2": {
                    "location": "v2",
                    "size": "0x4",
                    "value": "0xffffffde"
                }
            },
            "outputs": {
                "0": {
                    "location": "EAX",
                    "size": "0x4",
                    "value": "0xfffffeef"
                }
            }
        },
        "86": {
            "inputs": {
                "0": {
                    "location": "v0",
                    "size": "0x4",
                    "value": "0xffffffef"
                },
                "1": {
                    "location": "v1",
                    "size": "0x4",
                    "value": "0x2d"
                },
                "2": {
                    "location": "v2",
                    "size": "0x4",
                    "value": "0xa"
                }
            },
            "outputs": {
                "0": {
                    "location": "EAX",
                    "size": "0x4",
                    "value": "0xffffff7a"
                }
            }
        },
        "87": {
            "inputs": {
                "0": {
                    "location": "v0",
                    "size": "0x4",
                    "value": "0xfffffffd"
                },
                "1": {
                    "location": "v1",
                    "size": "0x4",
                    "value": "0x24"
                },
                "2": {
                    "location": "v2",
                    "size": "0x4",
                    "value": "0x1b"
                }
            },
            "outputs": {
                "0": {
                    "location": "EAX",
                    "size": "0x4",
                    "value": "0xffffff91"
                }
            }
        },
        "88": {
            "inputs": {
                "0": {
                    "location": "v0",
                    "size": "0x4",
                    "value": "0xfffffffb"
                },
                "1": {
                    "location": "v1",
                    "size": "0x4",
                    "value": "0xfffffffc"
                },
                "2": {
                    "location": "v2",
                    "size": "0x4",
                    "value": "0xffffffe5"
                }
            },
            "outputs": {
                "0": {
                    "location": "EAX",
                    "size": "0x4",
                    "value": "0xffffff7b"
                }
            }
        },
        "89": {
            "inputs": {
                "0": {
                    "location": "v0",
                    "size": "0x4",
                    "value": "0xffffffd0"
                },
                "1": {
                    "location": "v1",
                    "size": "0x4",
                    "value": "0x2f"
                },
                "2": {
                    "location": "v2",
                    "size": "0x4",
                    "value": "0xffffffd6"
                }
            },
            "outputs": {
                "0": {
                    "location": "EAX",
                    "size": "0x4",
                    "value": "0xfffff820"
                }
            }
        },
        "9": {
            "inputs": {
                "0": {
                    "location": "v0",
                    "size": "0x4",
                    "value": "0x29"
                },
                "1": {
                    "location": "v1",
                    "size": "0x4",
                    "value": "0xffffffdf"
                },
                "2": {
                    "location": "v2",
                    "size": "0x4",
                    "value": "0xffffffd1"
                }
            },
            "outputs": {
                "0": {
                    "location": "EAX",
                    "size": "0x4",
                    "value": "0x7a7"
                }
            }
        },
        "90": {
            "inputs": {
                "0": {
                    "location": "v0",
                    "size": "0x4",
                    "value": "0x23"
                },
                "1": {
                    "location": "v1",
                    "size": "0x4",
                    "value": "0x6"
                },
                "2": {
                    "location": "v2",
                    "size": "0x4",
                    "value": "0x2d"
                }
            },
            "outputs": {
                "0": {
                    "location": "EAX",
                    "size": "0x4",
                    "value": "0x609"
                }
            }
        },
        "91": {
            "inputs": {
                "0": {
                    "location": "v0",
                    "size": "0x4",
                    "value": "0x23"
                },
                "1": {
                    "location": "v1",
                    "size": "0x4",
                    "value": "0xffffffe9"
                },
                "2": {
                    "location": "v2",
                    "size": "0x4",
                    "value": "0xfffffff0"
                }
            },
            "outputs": {
                "0": {
                    "location": "EAX",
                    "size": "0x4",
                    "value": "0x236"
                }
            }
        },
        "92": {
            "inputs": {
                "0": {
                    "location": "v0",
                    "size": "0x4",
                    "value": "0xffffffce"
                },
                "1": {
                    "location": "v1",
                    "size": "0x4",
                    "value": "0x16"
                },
                "2": {
                    "location": "v2",
                    "size": "0x4",
                    "value": "0x18"
                }
            },
            "outputs": {
                "0": {
                    "location": "EAX",
                    "size": "0x4",
                    "value": "0xfffffb51"
                }
            }
        },
        "93": {
            "inputs": {
                "0": {
                    "location": "v0",
                    "size": "0x4",
                    "value": "0xffffffe2"
                },
                "1": {
                    "location": "v1",
                    "size": "0x4",
                    "value": "0xffffffe5"
                },
                "2": {
                    "location": "v2",
                    "size": "0x4",
                    "value": "0x1d"
                }
            },
            "outputs": {
                "0": {
                    "location": "EAX",
                    "size": "0x4",
                    "value": "0x364"
                }
            }
        },
        "94": {
            "inputs": {
                "0": {
                    "location": "v0",
                    "size": "0x4",
                    "value": "0xffffffe9"
                },
                "1": {
                    "location": "v1",
                    "size": "0x4",
                    "value": "0x1e"
                },
                "2": {
                    "location": "v2",
                    "size": "0x4",
                    "value": "0xffffffe5"
                }
            },
            "outputs": {
                "0": {
                    "location": "EAX",
                    "size": "0x4",
                    "value": "0xfffffd93"
                }
            }
        },
        "95": {
            "inputs": {
                "0": {
                    "location": "v0",
                    "size": "0x4",
                    "value": "0x28"
                },
                "1": {
                    "location": "v1",
                    "size": "0x4",
                    "value": "0xffffffdc"
                },
                "2": {
                    "location": "v2",
                    "size": "0x4",
                    "value": "0x31"
                }
            },
            "outputs": {
                "0": {
                    "location": "EAX",
                    "size": "0x4",
                    "value": "0xfffff85a"
                }
            }
        },
        "96": {
            "inputs": {
                "0": {
                    "location": "v0",
                    "size": "0x4",
                    "value": "0x32"
                },
                "1": {
                    "location": "v1",
                    "size": "0x4",
                    "value": "0x1e"
                },
                "2": {
                    "location": "v2",
                    "size": "0x4",
                    "value": "0xfffffff3"
                }
            },
            "outputs": {
                "0": {
                    "location": "EAX",
                    "size": "0x4",
                    "value": "0x28a"
                }
            }
        },
        "97": {
            "inputs": {
                "0": {
                    "location": "v0",
                    "size": "0x4",
                    "value": "0xffffffd6"
                },
                "1": {
                    "location": "v1",
                    "size": "0x4",
                    "value": "0xffffffd4"
                },
                "2": {
                    "location": "v2",
                    "size": "0x4",
                    "value": "0x7"
                }
            },
            "outputs": {
                "0": {
                    "location": "EAX",
                    "size": "0x4",
                    "value": "0x10e"
                }
            }
        },
        "98": {
            "inputs": {
                "0": {
                    "location": "v0",
                    "size": "0x4",
                    "value": "0x8"
                },
                "1": {
                    "location": "v1",
                    "size": "0x4",
                    "value": "0xfffffffc"
                },
                "2": {
                    "location": "v2",
                    "size": "0x4",
                    "value": "0x2c"
                }
            },
            "outputs": {
                "0": {
                    "location": "EAX",
                    "size": "0x4",
                    "value": "0xfffffea3"
                }
            }
        },
        "99": {
            "inputs": {
                "0": {
                    "location": "v0",
                    "size": "0x4",
                    "value": "0x15"
                },
                "1": {
                    "location": "v1",
                    "size": "0x4",
                    "value": "0x5"
                },
                "2": {
                    "location": "v2",
                    "size": "0x4",
                    "value": "0xf"
                }
            },
            "outputs": {
                "0": {
                    "location": "EAX",
                    "size": "0x4",
                    "value": "0x135"
                }
            }
        }
    }
}
